promptflow/tracing/__init__.py
promptflow/tracing/_constants.py
promptflow/tracing/_context_utils.py
promptflow/tracing/_experimental/__init__.py
promptflow/tracing/_integrations/__init__.py
promptflow/tracing/_integrations/_openai_injector.py
promptflow/tracing/_openai_utils.py
promptflow/tracing/_operation_context.py
promptflow/tracing/_span_enricher.py
promptflow/tracing/_start_trace.py
promptflow/tracing/_thread_local_singleton.py
promptflow/tracing/_trace.py
promptflow/tracing/_tracer.py
promptflow/tracing/_utils.py
promptflow/tracing/_version.py
promptflow/tracing/contracts/__init__.py
promptflow/tracing/contracts/context_manager_proxy.py
promptflow/tracing/contracts/iterator_proxy.py
promptflow/tracing/contracts/trace.py
promptflow_tracing-1.18.2.dist-info/METADATA
promptflow_tracing-1.18.2.dist-info/WHEEL
promptflow_tracing-1.18.2.dist-info/RECORD
