Metadata-Version: 2.4
Name: promptflow-tracing
Version: 1.18.2
Summary: Prompt flow tracing
License: MIT
Keywords: telemetry
Author: Microsoft Corporation
Author-email: aml-pt-eng@microsoft.com
Requires-Python: >=3.9,<4.0
Classifier: License :: OSI Approved :: MIT License
Classifier: Operating System :: OS Independent
Classifier: Programming Language :: Python
Classifier: Programming Language :: Python :: 3
Classifier: Programming Language :: Python :: 3.9
Classifier: Programming Language :: Python :: 3.10
Classifier: Programming Language :: Python :: 3.11
Classifier: Programming Language :: Python :: 3.12
Classifier: Programming Language :: Python :: 3.13
Classifier: Programming Language :: Python :: 3.14
Classifier: Programming Language :: Python :: 3 :: Only
Requires-Dist: openai
Requires-Dist: opentelemetry-sdk (>=1.22.0,<1.39.0)
Requires-Dist: tiktoken (>=0.4.0)
Project-URL: Bug Reports, https://github.com/microsoft/promptflow/issues
Project-URL: Homepage, https://microsoft.github.io/promptflow/
Project-URL: Repository, https://github.com/microsoft/promptflow
